django_umd_lib_style-1.2.0.dist-info/licenses/LICENSE.md
umd_lib_style/__init__.py
umd_lib_style/apps.py
umd_lib_style/context_processors.py
umd_lib_style/static/umd_lib_style/liblogo.png
umd_lib_style/static/umd_lib_style/umd_lib_style.css
umd_lib_style/templates/umd_lib_style/base.html
umd_lib_style/templates/umd_lib_style/footer.html
umd_lib_style/templates/umd_lib_style/header.html
umd_lib_style/templates/umd_lib_style/nav_menu_item.html
umd_lib_style/templatetags/__init__.py
umd_lib_style/templatetags/umd_lib_style.py
django_umd_lib_style-1.2.0.dist-info/METADATA
django_umd_lib_style-1.2.0.dist-info/WHEEL
django_umd_lib_style-1.2.0.dist-info/top_level.txt
django_umd_lib_style-1.2.0.dist-info/RECORD
