Metadata-Version: 2.4
Name: django-umd-lib-style
Version: 1.2.0
Summary: Django app that provides theming for UMD Libraries applications
Author-email: University of Maryland Libraries <lib-ssdr@umd.edu>, Erik Jones <ejones99@umd.edu>, Peter Eichman <peichman@umd.edu>, Tim Kanke <tkanke@umd.edu>
License-Expression: Apache-2.0
Classifier: Development Status :: 5 - Production/Stable
Classifier: Programming Language :: Python :: 3 :: Only
Classifier: Framework :: Django
Classifier: Operating System :: OS Independent
License-File: LICENSE.md
Requires-Dist: django>=4.2
Provides-Extra: test
Requires-Dist: pytest; extra == "test"
Requires-Dist: pytest-django; extra == "test"
Dynamic: license-file
